setup.py
./shiver/__init__.py
./shiver/example_mm.py
./shiver/llvm_helpers.py
./shiver/shiver.py
./shiver/test.py
./shiver/testing_helpers.py
./shiver/type_helpers.py
./shiver/wrappers.py
shiver.egg-info/PKG-INFO
shiver.egg-info/SOURCES.txt
shiver.egg-info/dependency_links.txt
shiver.egg-info/top_level.txt