Metadata-Version: 1.1
Name: shiver
Version: 0.11
Summary: A multi-threaded work queue for functions compiled with llvmpy
Home-page: http://github.com/iskandr/shiver
Author: Alex Rubinsteyn
Author-email: alexr@cs.nyu.edu
License: BSD
Platform: UNKNOWN
Classifier: Development Status :: 3 - Alpha
Classifier: Topic :: Software Development :: Libraries
Classifier: License :: OSI Approved :: BSD License
Classifier: Intended Audience :: Developers
Classifier: Programming Language :: Python :: 2.7
Requires: llvmpy
Requires: numpy
Requires: scipy
